wllvm/__init__.py
wllvm/arglistfilter.py
wllvm/as.py
wllvm/checker.py
wllvm/compilers.py
wllvm/extraction.py
wllvm/extractor.py
wllvm/filetype.py
wllvm/logconfig.py
wllvm/popenwrapper.py
wllvm/sanity.py
wllvm/version.py
wllvm/wfortran.py
wllvm/wllvm.py
wllvm/wllvmpp.py
wllvm/wparser.py
wllvm/dragonegg_as/as
wllvm-1.3.1.dist-info/LICENSE
wllvm-1.3.1.dist-info/METADATA
wllvm-1.3.1.dist-info/WHEEL
wllvm-1.3.1.dist-info/entry_points.txt
wllvm-1.3.1.dist-info/top_level.txt
wllvm-1.3.1.dist-info/RECORD
