Metadata-Version: 1.2
Name: wllvm
Version: 1.3.1
Summary: Whole Program LLVM
Home-page: https://github.com/SRI-CSL/whole-program-llvm
Author: Ian A. Mason, Tristan Ravitch, Dan Liew, Bruno Dutertre, Benjamin Schubert, Berkeley Churchill, Marko Dimjasevic, Will Dietz, Fabian Mager, Ben Liblit, Andrew Santosa, Tomas Kalibera, Loic  Gelle, Joshua Cranmer, Alexander Bakst, Miguel Arroyo.
Author-email: iam@csl.sri.com
License: MIT
Platform: UNKNOWN
Classifier: Development Status :: 4 - Beta
Classifier: Natural Language :: English
Classifier: Intended Audience :: Science/Research
Classifier: Intended Audience :: Developers
Classifier: Topic :: Software Development :: Compilers
Classifier: License :: OSI Approved :: MIT License
Classifier: Operating System :: OS Independent
Classifier: Operating System :: MacOS
Classifier: Operating System :: POSIX :: Linux
Classifier: Operating System :: POSIX :: BSD
Classifier: Programming Language :: Python
Classifier: Programming Language :: Python :: 2
Classifier: Programming Language :: Python :: 2.7
Classifier: Programming Language :: Python :: 3
Requires-Python: >=3.6
